pigmenta/__init__.py
pigmenta/palettes.py
pigmenta/static/colorhunt.json
pigmenta/tests/test_pigmenta.py
pigmenta-0.0.2.dist-info/licenses/LICENSE
pigmenta-0.0.2.dist-info/METADATA
pigmenta-0.0.2.dist-info/WHEEL
pigmenta-0.0.2.dist-info/top_level.txt
pigmenta-0.0.2.dist-info/RECORD
