Metadata-Version: 2.4
Name: pigmenta
Version: 0.0.2
Summary: This packages contains some color Palettes that are very important for visualizing graphs and doing other stuffs.
Author-email: Crispen Gari <crispengari@gmail.com>
License: MIT License
Project-URL: homepage, https://github.com/CrispenGari/pigmenta
Project-URL: repository, https://github.com/CrispenGari/pigmenta
Project-URL: documentation, https://github.com/CrispenGari/pigmenta/blob/main/README.md
Project-URL: changelog, https://github.com/CrispenGari/pigmenta/blob/main/CHANGELOG.md
Project-URL: issues, https://github.com/CrispenGari/pigmenta/issues
Keywords: pigmenta,python,python3,color palettes,colors,coloring,machine-learning
Classifier: Development Status :: 6 - Mature
Classifier: Intended Audience :: Developers
Classifier: License :: OSI Approved :: MIT License
Classifier: Programming Language :: Python :: 3.9
Classifier: Topic :: Software Development :: Libraries :: Python Modules
Classifier: Topic :: Terminals
Classifier: Topic :: Utilities
Classifier: Programming Language :: Python
Classifier: Programming Language :: Python :: 3.12
Classifier: Programming Language :: Python :: 3.11
Classifier: Programming Language :: Python :: 3.10
Classifier: Operating System :: Unix
Classifier: Operating System :: MacOS :: MacOS X
Classifier: Operating System :: Microsoft :: Windows
Classifier: Natural Language :: English
Requires-Python: >=3.9
License-File: LICENSE
Dynamic: license-file
